{
  "version": "0.2",
  "language": "en",
  "ignorePaths": [
    "node_modules/**",
    ".git/**",
    "*.lock",
    "*.min.js",
    "*.min.css",
    "**/*.bats"
  ],
  "words": [
    "actionlint",
    "alxleo",
    "checkmark",
    "commitlint",
    "cspell",
    "dogfood",
    "Dockerfiles",
    "endgroup",
    "esac",
    "eslint",
    "Gitea",
    "gitleaks",
    "hadolint",
    "justfile",
    "justfiles",
    "knip",
    "logdir",
    "logfile",
    "logkey",
    "markdownlint",
    "mktemp",
    "pipefail",
    "prettierrc",
    "pythonic",
    "semgrep",
    "shellcheck",
    "shellcheckrc",
    "startswith",
    "tflint",
    "trivy",
    "yamllint",
    "zizmor"
  ],
  "flagWords": []
}
